pyqt_builder-1.19.1.dist-info/licenses/LICENSE
pyqtbuild/__init__.py
pyqtbuild/_version.py
pyqtbuild/bindings.py
pyqtbuild/builder.py
pyqtbuild/installable.py
pyqtbuild/project.py
pyqtbuild/version.py
pyqtbuild/bundle/__init__.py
pyqtbuild/bundle/abstract_package.py
pyqtbuild/bundle/bundle.py
pyqtbuild/bundle/bundle_main.py
pyqtbuild/bundle/qt_metadata.py
pyqtbuild/bundle/qt_wheel.py
pyqtbuild/bundle/qt_wheel_main.py
pyqtbuild/bundle/verbose.py
pyqtbuild/bundle/wheel.py
pyqtbuild/bundle/dlls/msvc-32/concrt140.dll
pyqtbuild/bundle/dlls/msvc-32/msvcp140.dll
pyqtbuild/bundle/dlls/msvc-32/msvcp140_1.dll
pyqtbuild/bundle/dlls/msvc-32/msvcp140_2.dll
pyqtbuild/bundle/dlls/msvc-32/msvcp140_atomic_wait.dll
pyqtbuild/bundle/dlls/msvc-32/msvcp140_codecvt_ids.dll
pyqtbuild/bundle/dlls/msvc-32/vccorlib140.dll
pyqtbuild/bundle/dlls/msvc-32/vcruntime140.dll
pyqtbuild/bundle/dlls/msvc-32/vcruntime140_threads.dll
pyqtbuild/bundle/dlls/msvc-64/concrt140.dll
pyqtbuild/bundle/dlls/msvc-64/msvcp140.dll
pyqtbuild/bundle/dlls/msvc-64/msvcp140_1.dll
pyqtbuild/bundle/dlls/msvc-64/msvcp140_2.dll
pyqtbuild/bundle/dlls/msvc-64/msvcp140_atomic_wait.dll
pyqtbuild/bundle/dlls/msvc-64/msvcp140_codecvt_ids.dll
pyqtbuild/bundle/dlls/msvc-64/vccorlib140.dll
pyqtbuild/bundle/dlls/msvc-64/vcruntime140.dll
pyqtbuild/bundle/dlls/msvc-64/vcruntime140_1.dll
pyqtbuild/bundle/dlls/msvc-64/vcruntime140_threads.dll
pyqtbuild/bundle/dlls/msvc-arm64/concrt140.dll
pyqtbuild/bundle/dlls/msvc-arm64/msvcp140.dll
pyqtbuild/bundle/dlls/msvc-arm64/msvcp140_1.dll
pyqtbuild/bundle/dlls/msvc-arm64/msvcp140_2.dll
pyqtbuild/bundle/dlls/msvc-arm64/msvcp140_atomic_wait.dll
pyqtbuild/bundle/dlls/msvc-arm64/msvcp140_codecvt_ids.dll
pyqtbuild/bundle/dlls/msvc-arm64/vccorlib140.dll
pyqtbuild/bundle/dlls/msvc-arm64/vcruntime140.dll
pyqtbuild/bundle/dlls/msvc-arm64/vcruntime140_1.dll
pyqtbuild/bundle/dlls/msvc-arm64/vcruntime140_threads.dll
pyqtbuild/bundle/dlls/openssl-32/libcrypto-1_1.dll
pyqtbuild/bundle/dlls/openssl-32/libssl-1_1.dll
pyqt_builder-1.19.1.dist-info/METADATA
pyqt_builder-1.19.1.dist-info/WHEEL
pyqt_builder-1.19.1.dist-info/entry_points.txt
pyqt_builder-1.19.1.dist-info/top_level.txt
pyqt_builder-1.19.1.dist-info/RECORD
