Metadata-Version: 2.4
Name: PyQt-builder
Version: 1.19.1
Summary: The PyQt build system
Author-email: Phil Thompson <phil@riverbankcomputing.com>
License-Expression: BSD-2-Clause
Project-URL: homepage, https://github.com/Python-PyQt/PyQt-builder
Requires-Python: >=3.8
License-File: LICENSE
Requires-Dist: packaging
Requires-Dist: sip<7,>=6.7
Dynamic: license-file
